unreadable/__init__.py
unreadable-0.0.1.dist-info/LICENCE
unreadable-0.0.1.dist-info/METADATA
unreadable-0.0.1.dist-info/WHEEL
unreadable-0.0.1.dist-info/top_level.txt
unreadable-0.0.1.dist-info/RECORD
